{
  "eventType": "Offlinesyncpreview",
  "firstSeen": "2025-09-07T03:19:22.501Z",
  "lastSeen": "2025-09-15T02:48:01.249Z",
  "totalReceived": 31,
  "schemaVersion": 30,
  "lastModified": "2025-09-15T02:48:01.191Z",
  "fields": {
    "required": [
      "headers",
      "headers.host",
      "headers.user-agent",
      "headers.content-length",
      "headers.accept",
      "headers.content-type",
      "headers.accept-encoding",
      "body",
      "body.data",
      "body.data.event",
      "body.data.event.Total",
      "body.data.event.AppDataChanges",
      "body.data.event.Messages",
      "body.data.event.Notifications",
      "body.data.event.Receipts",
      "body.data.type",
      "body.eventType",
      "body.timestamp",
      "body.token",
      "body.userID",
      "body.userJID",
      "body.userName"
    ],
    "optional": [
      "body.baseURL"
    ],
    "truncated": []
  },
  "variations": [],
  "savedStructure": {
    "path": "",
    "type": "object",
    "optional": false,
    "examples": [
      {
        "headers": {
          "host": "185.245.182.69:3000",
          "user-agent": "ZuckZapGo-Webhook/1.0",
          "content-length": "375",
          "accept": "application/json",
          "content-type": "application/json",
          "accept-encoding": "gzip"
        },
        "body": {
          "baseURL": "https://api.zuckzapgo.com",
          "data": {
            "event": {
              "Total": 438,
              "AppDataChanges": 0,
              "Messages": 90,
              "Notifications": 228,
              "Receipts": 119
            },
            "type": "OfflineSyncPreview"
          },
          "eventType": "OfflineSyncPreview",
          "timestamp": 1757832834,
          "token": "!!qYWdJ61zk3i1AvTfXhzE!!",
          "userID": "9e832a8666e02c047a5167194c703eaf",
          "userJID": "5521971532700:4@s.whatsapp.net",
          "userName": "setupautomatizado"
        }
      },
      {
        "headers": {
          "host": "185.245.182.69:3000",
          "user-agent": "ZuckZapGo-Webhook/1.0",
          "content-length": "368",
          "accept": "application/json",
          "content-type": "application/json",
          "accept-encoding": "gzip"
        },
        "body": {
          "baseURL": "https://api.zuckzapgo.com",
          "data": {
            "event": {
              "Total": 4,
              "AppDataChanges": 0,
              "Messages": 3,
              "Notifications": 0,
              "Receipts": 0
            },
            "type": "OfflineSyncPreview"
          },
          "eventType": "OfflineSyncPreview",
          "timestamp": 1757904358,
          "token": "!!qYWdJ61zk3i1AvTfXhzE!!",
          "userID": "9e832a8666e02c047a5167194c703eaf",
          "userJID": "5521971532700:4@s.whatsapp.net",
          "userName": "setupautomatizado"
        }
      },
      {
        "headers": {
          "host": "185.245.182.69:3000",
          "user-agent": "ZuckZapGo-Webhook/1.0",
          "content-length": "368",
          "accept": "application/json",
          "content-type": "application/json",
          "accept-encoding": "gzip"
        },
        "body": {
          "baseURL": "https://api.zuckzapgo.com",
          "data": {
            "event": {
              "Total": 2,
              "AppDataChanges": 0,
              "Messages": 1,
              "Notifications": 0,
              "Receipts": 0
            },
            "type": "OfflineSyncPreview"
          },
          "eventType": "OfflineSyncPreview",
          "timestamp": 1757904388,
          "token": "!!qYWdJ61zk3i1AvTfXhzE!!",
          "userID": "9e832a8666e02c047a5167194c703eaf",
          "userJID": "5521971532700:4@s.whatsapp.net",
          "userName": "setupautomatizado"
        }
      },
      {
        "headers": {
          "host": "185.245.182.69:3000",
          "user-agent": "ZuckZapGo-Webhook/1.0",
          "content-length": "368",
          "accept": "application/json",
          "content-type": "application/json",
          "accept-encoding": "gzip"
        },
        "body": {
          "baseURL": "https://api.zuckzapgo.com",
          "data": {
            "event": {
              "Total": 7,
              "AppDataChanges": 0,
              "Messages": 6,
              "Notifications": 0,
              "Receipts": 0
            },
            "type": "OfflineSyncPreview"
          },
          "eventType": "OfflineSyncPreview",
          "timestamp": 1757904434,
          "token": "!!qYWdJ61zk3i1AvTfXhzE!!",
          "userID": "9e832a8666e02c047a5167194c703eaf",
          "userJID": "5521971532700:4@s.whatsapp.net",
          "userName": "setupautomatizado"
        }
      },
      {
        "headers": {
          "host": "185.245.182.69:3000",
          "user-agent": "ZuckZapGo-Webhook/1.0",
          "content-length": "368",
          "accept": "application/json",
          "content-type": "application/json",
          "accept-encoding": "gzip"
        },
        "body": {
          "baseURL": "https://api.zuckzapgo.com",
          "data": {
            "event": {
              "Total": 2,
              "AppDataChanges": 0,
              "Messages": 1,
              "Notifications": 0,
              "Receipts": 0
            },
            "type": "OfflineSyncPreview"
          },
          "eventType": "OfflineSyncPreview",
          "timestamp": 1757904475,
          "token": "!!qYWdJ61zk3i1AvTfXhzE!!",
          "userID": "9e832a8666e02c047a5167194c703eaf",
          "userJID": "5521971532700:4@s.whatsapp.net",
          "userName": "setupautomatizado"
        }
      }
    ],
    "children": {
      "headers": {
        "path": "headers",
        "type": "object",
        "optional": false,
        "examples": [
          {
            "host": "185.245.182.69:3000",
            "user-agent": "ZuckZapGo-Webhook/1.0",
            "content-length": "369",
            "accept": "application/json",
            "content-type": "application/json",
            "accept-encoding": "gzip"
          },
          {
            "host": "185.245.182.69:3000",
            "user-agent": "ZuckZapGo-Webhook/1.0",
            "content-length": "379",
            "accept": "application/json",
            "content-type": "application/json",
            "accept-encoding": "gzip"
          },
          {
            "host": "185.245.182.69:3000",
            "user-agent": "ZuckZapGo-Webhook/1.0",
            "content-length": "382",
            "accept": "application/json",
            "content-type": "application/json",
            "accept-encoding": "gzip"
          },
          {
            "host": "185.245.182.69:3000",
            "user-agent": "ZuckZapGo-Webhook/1.0",
            "content-length": "375",
            "accept": "application/json",
            "content-type": "application/json",
            "accept-encoding": "gzip"
          },
          {
            "host": "185.245.182.69:3000",
            "user-agent": "ZuckZapGo-Webhook/1.0",
            "content-length": "368",
            "accept": "application/json",
            "content-type": "application/json",
            "accept-encoding": "gzip"
          }
        ],
        "children": {
          "host": {
            "path": "headers.host",
            "type": "string",
            "optional": false,
            "examples": [
              "185.245.182.69:3000"
            ]
          },
          "user-agent": {
            "path": "headers.user-agent",
            "type": "string",
            "optional": false,
            "examples": [
              "ZuckZapGo-Webhook/1.0"
            ]
          },
          "content-length": {
            "path": "headers.content-length",
            "type": "string",
            "optional": false,
            "examples": [
              "369",
              "379",
              "382",
              "375",
              "368"
            ]
          },
          "accept": {
            "path": "headers.accept",
            "type": "string",
            "optional": false,
            "examples": [
              "application/json"
            ]
          },
          "content-type": {
            "path": "headers.content-type",
            "type": "string",
            "optional": false,
            "examples": [
              "application/json"
            ]
          },
          "accept-encoding": {
            "path": "headers.accept-encoding",
            "type": "string",
            "optional": false,
            "examples": [
              "gzip"
            ]
          }
        }
      },
      "body": {
        "path": "body",
        "type": "object",
        "optional": false,
        "examples": [
          {
            "baseURL": "https://api.zuckzapgo.com",
            "data": {
              "event": {
                "Total": 438,
                "AppDataChanges": 0,
                "Messages": 90,
                "Notifications": 228,
                "Receipts": 119
              },
              "type": "OfflineSyncPreview"
            },
            "eventType": "OfflineSyncPreview",
            "timestamp": 1757832834,
            "token": "!!qYWdJ61zk3i1AvTfXhzE!!",
            "userID": "9e832a8666e02c047a5167194c703eaf",
            "userJID": "5521971532700:4@s.whatsapp.net",
            "userName": "setupautomatizado"
          },
          {
            "baseURL": "https://api.zuckzapgo.com",
            "data": {
              "event": {
                "Total": 4,
                "AppDataChanges": 0,
                "Messages": 3,
                "Notifications": 0,
                "Receipts": 0
              },
              "type": "OfflineSyncPreview"
            },
            "eventType": "OfflineSyncPreview",
            "timestamp": 1757904358,
            "token": "!!qYWdJ61zk3i1AvTfXhzE!!",
            "userID": "9e832a8666e02c047a5167194c703eaf",
            "userJID": "5521971532700:4@s.whatsapp.net",
            "userName": "setupautomatizado"
          },
          {
            "baseURL": "https://api.zuckzapgo.com",
            "data": {
              "event": {
                "Total": 2,
                "AppDataChanges": 0,
                "Messages": 1,
                "Notifications": 0,
                "Receipts": 0
              },
              "type": "OfflineSyncPreview"
            },
            "eventType": "OfflineSyncPreview",
            "timestamp": 1757904388,
            "token": "!!qYWdJ61zk3i1AvTfXhzE!!",
            "userID": "9e832a8666e02c047a5167194c703eaf",
            "userJID": "5521971532700:4@s.whatsapp.net",
            "userName": "setupautomatizado"
          },
          {
            "baseURL": "https://api.zuckzapgo.com",
            "data": {
              "event": {
                "Total": 7,
                "AppDataChanges": 0,
                "Messages": 6,
                "Notifications": 0,
                "Receipts": 0
              },
              "type": "OfflineSyncPreview"
            },
            "eventType": "OfflineSyncPreview",
            "timestamp": 1757904434,
            "token": "!!qYWdJ61zk3i1AvTfXhzE!!",
            "userID": "9e832a8666e02c047a5167194c703eaf",
            "userJID": "5521971532700:4@s.whatsapp.net",
            "userName": "setupautomatizado"
          },
          {
            "baseURL": "https://api.zuckzapgo.com",
            "data": {
              "event": {
                "Total": 2,
                "AppDataChanges": 0,
                "Messages": 1,
                "Notifications": 0,
                "Receipts": 0
              },
              "type": "OfflineSyncPreview"
            },
            "eventType": "OfflineSyncPreview",
            "timestamp": 1757904475,
            "token": "!!qYWdJ61zk3i1AvTfXhzE!!",
            "userID": "9e832a8666e02c047a5167194c703eaf",
            "userJID": "5521971532700:4@s.whatsapp.net",
            "userName": "setupautomatizado"
          }
        ],
        "children": {
          "data": {
            "path": "body.data",
            "type": "object",
            "optional": false,
            "examples": [
              {
                "event": {
                  "Total": 81,
                  "AppDataChanges": 0,
                  "Messages": 58,
                  "Notifications": 22,
                  "Receipts": 0
                },
                "type": "OfflineSyncPreview"
              },
              {
                "event": {
                  "Total": 438,
                  "AppDataChanges": 0,
                  "Messages": 90,
                  "Notifications": 228,
                  "Receipts": 119
                },
                "type": "OfflineSyncPreview"
              },
              {
                "event": {
                  "Total": 4,
                  "AppDataChanges": 0,
                  "Messages": 3,
                  "Notifications": 0,
                  "Receipts": 0
                },
                "type": "OfflineSyncPreview"
              },
              {
                "event": {
                  "Total": 2,
                  "AppDataChanges": 0,
                  "Messages": 1,
                  "Notifications": 0,
                  "Receipts": 0
                },
                "type": "OfflineSyncPreview"
              },
              {
                "event": {
                  "Total": 7,
                  "AppDataChanges": 0,
                  "Messages": 6,
                  "Notifications": 0,
                  "Receipts": 0
                },
                "type": "OfflineSyncPreview"
              }
            ],
            "children": {
              "event": {
                "path": "body.data.event",
                "type": "object",
                "optional": false,
                "examples": [
                  {
                    "Total": 81,
                    "AppDataChanges": 0,
                    "Messages": 58,
                    "Notifications": 22,
                    "Receipts": 0
                  },
                  {
                    "Total": 438,
                    "AppDataChanges": 0,
                    "Messages": 90,
                    "Notifications": 228,
                    "Receipts": 119
                  },
                  {
                    "Total": 4,
                    "AppDataChanges": 0,
                    "Messages": 3,
                    "Notifications": 0,
                    "Receipts": 0
                  },
                  {
                    "Total": 2,
                    "AppDataChanges": 0,
                    "Messages": 1,
                    "Notifications": 0,
                    "Receipts": 0
                  },
                  {
                    "Total": 7,
                    "AppDataChanges": 0,
                    "Messages": 6,
                    "Notifications": 0,
                    "Receipts": 0
                  }
                ],
                "children": {
                  "Total": {
                    "path": "body.data.event.Total",
                    "type": "number",
                    "optional": false,
                    "examples": [
                      81,
                      438,
                      4,
                      7,
                      2
                    ]
                  },
                  "AppDataChanges": {
                    "path": "body.data.event.AppDataChanges",
                    "type": "number",
                    "optional": false,
                    "examples": [
                      0
                    ]
                  },
                  "Messages": {
                    "path": "body.data.event.Messages",
                    "type": "number",
                    "optional": false,
                    "examples": [
                      58,
                      90,
                      3,
                      1,
                      6
                    ]
                  },
                  "Notifications": {
                    "path": "body.data.event.Notifications",
                    "type": "number",
                    "optional": false,
                    "examples": [
                      5,
                      2,
                      22,
                      228,
                      0
                    ]
                  },
                  "Receipts": {
                    "path": "body.data.event.Receipts",
                    "type": "number",
                    "optional": false,
                    "examples": [
                      12,
                      0,
                      8,
                      7,
                      119
                    ]
                  }
                }
              },
              "type": {
                "path": "body.data.type",
                "type": "string",
                "optional": false,
                "examples": [
                  "OfflineSyncPreview"
                ]
              }
            }
          },
          "eventType": {
            "path": "body.eventType",
            "type": "string",
            "optional": false,
            "examples": [
              "OfflineSyncPreview"
            ]
          },
          "timestamp": {
            "path": "body.timestamp",
            "type": "number",
            "optional": false,
            "examples": [
              1757832834,
              1757904358,
              1757904388,
              1757904434,
              1757904475
            ]
          },
          "token": {
            "path": "body.token",
            "type": "string",
            "optional": false,
            "examples": [
              "hibrido",
              "!!qYWdJ61zk3i1AvTfXhzE!!",
              "!!!qYWdJ61zk3i1AvTfXhzE!!!"
            ]
          },
          "userID": {
            "path": "body.userID",
            "type": "string",
            "optional": false,
            "examples": [
              "baf81c72f383e3c7814c18aab2d72360",
              "9e832a8666e02c047a5167194c703eaf",
              "80402f2ab5855b2132cf45d6b365a62c"
            ]
          },
          "userJID": {
            "path": "body.userJID",
            "type": "string",
            "optional": false,
            "examples": [
              "5521979232690:28@s.whatsapp.net",
              "5521971532700:4@s.whatsapp.net",
              "5521979232690:36@s.whatsapp.net"
            ]
          },
          "userName": {
            "path": "body.userName",
            "type": "string",
            "optional": false,
            "examples": [
              "hibrido",
              "setupautomatizado",
              "setupautomatizado-hibrido"
            ]
          },
          "baseURL": {
            "path": "body.baseURL",
            "type": "string",
            "optional": true,
            "examples": [
              "",
              "https://api.zuckzapgo.com"
            ]
          }
        }
      }
    }
  }
}