{
  "headers": {
    "connection": "Upgrade, HTTP2-Settings",
    "content-length": "1166",
    "host": "185.245.182.69:3000",
    "http2-settings": "AAEAAEAAAAIAAAAAAAMAAAAAAAQBAAAAAAUAAEAAAAYABgAA",
    "upgrade": "h2c",
    "content-type": "application/json",
    "origin": "https://api.z-api.io",
    "server": "Z-API",
    "user-agent": "Mozilla/5.0 (Windows NT 10.0; Win64; x64; rv:111.0) Gecko/20100101 Firefox/111.0",
    "z-api-token": "0B039DE5C908EDAF88346CED"
  },
  "body": {
    "isStatusReply": false,
    "chatLid": null,
    "connectedPhone": "5521971532700",
    "waitingMessage": false,
    "isEdit": false,
    "isGroup": true,
    "isNewsletter": false,
    "instanceId": "3E6D06A438D501A5CD70265FDA264287",
    "messageId": "3EB0E4FD07437E192AD5D2",
    "phone": "120363036972484891-group",
    "fromMe": false,
    "momment": 1757385610000,
    "status": "RECEIVED",
    "chatName": "Nodejs - Whatsapp APIS",
    "senderPhoto": "https://pps.whatsapp.net/v/t61.24694-24/520822953_757224160325277_6300452363841589012_n.jpg?ccb=11-4&oh=01_Q5Aa2gEf3QYKNWLwsFotEWyUFFzQCQ9kfidbjSecY2tCtbuRHw&oe=68CC8B0B&_nc_sid=5e03e0&_nc_cat=100",
    "senderName": "Will",
    "photo": "https://pps.whatsapp.net/v/t61.24694-24/263875138_169163215403082_1951773804801254549_n.jpg?ccb=11-4&oh=01_Q5Aa2gHHwGyY763k7UL2VXC7QXsHqdjXIQAWNTqTtojB_tjJ6A&oe=68CC986B&_nc_sid=5e03e0&_nc_cat=102",
    "broadcast": false,
    "participantPhone": "554898002979",
    "participantLid": "216316111794181@lid",
    "forwarded": false,
    "type": "ReceivedCallback",
    "fromApi": false,
    "reaction": {
      "value": "🙏",
      "time": 1757385602000,
      "reactionBy": "554898002979",
      "referencedMessage": {
        "messageId": "3EB00219B0ED0AF3663863",
        "fromMe": false,
        "phone": "120363036972484891-group",
        "participant": "556492134371"
      }
    }
  }
}