{
  "headers": {
    "host": "185.245.182.69:3000",
    "user-agent": "ZuckZapGo-Webhook/1.0",
    "content-length": "729",
    "accept": "application/json",
    "content-type": "application/json",
    "accept-encoding": "gzip"
  },
  "body": {
    "baseURL": "https://api.zuckzapgo.com",
    "data": {
      "event": {
        "Index": [
          "call_log",
          "5521971532700@s.whatsapp.net",
          "A583A766A084735E5EAEAB5A2ACC800E",
          "0"
        ],
        "timestamp": 1757899661209,
        "callLogAction": {
          "callLogRecord": {
            "callResult": 4,
            "isDndMode": false,
            "silenceReason": 0,
            "duration": 0,
            "startTime": 1757899618,
            "isIncoming": false,
            "isVideo": true,
            "callID": "A583A766A084735E5EAEAB5A2ACC800E",
            "callCreatorJID": "5521971532700@s.whatsapp.net",
            "participants": [
              {
                "userJID": "5521971893103@s.whatsapp.net",
                "callResult": 4
              }
            ],
            "callType": 0
          }
        }
      },
      "type": "AppState"
    },
    "eventType": "AppState",
    "timestamp": 1757899660,
    "token": "!!qYWdJ61zk3i1AvTfXhzE!!",
    "userID": "9e832a8666e02c047a5167194c703eaf",
    "userJID": "5521971532700:4@s.whatsapp.net",
    "userName": "setupautomatizado"
  }
}